vishuml/__init__.py
vishuml/decision_tree.py
vishuml/kmeans.py
vishuml/knn.py
vishuml/linear_regression.py
vishuml/logistic_regression.py
vishuml/naive_bayes.py
vishuml/perceptron.py
vishuml/svm.py
vishuml/utils.py
vishuml/datasets/__init__.py
vishuml/datasets/housing.csv
vishuml/datasets/iris.csv
vishuml/datasets/wine.csv
vishuml-0.1.8.dist-info/licenses/LICENSE
vishuml-0.1.8.dist-info/METADATA
vishuml-0.1.8.dist-info/WHEEL
vishuml-0.1.8.dist-info/top_level.txt
vishuml-0.1.8.dist-info/RECORD
