Metadata-Version: 2.4
Name: vishuml
Version: 0.1.8
Summary: A machine learning library implementing algorithms from scratch
Home-page: https://github.com/vishuRizz/vishuml-pip-library
Author: Vishu pratap
Author-email: vishurizz0@gmail.com
Project-URL: Bug Reports, https://github.com/vishuRizz/vishuml-pip-library/issues
Project-URL: Source, https://github.com/vishuRizz/vishuml-pip-library
Project-URL: Documentation, https://github.com/vishuRizz/vishuml-pip-library#readme
Keywords: machine learning,algorithms,classification,regression,clustering,data science
Classifier: Development Status :: 3 - Alpha
Classifier: Intended Audience :: Developers
Classifier: Intended Audience :: Education
Classifier: Intended Audience :: Science/Research
Classifier: License :: OSI Approved :: MIT License
Classifier: Operating System :: OS Independent
Classifier: Programming Language :: Python :: 3
Classifier: Programming Language :: Python :: 3.7
Classifier: Programming Language :: Python :: 3.8
Classifier: Programming Language :: Python :: 3.9
Classifier: Programming Language :: Python :: 3.10
Classifier: Programming Language :: Python :: 3.11
Classifier: Topic :: Scientific/Engineering :: Artificial Intelligence
Classifier: Topic :: Software Development :: Libraries :: Python Modules
Requires-Python: >=3.7
License-File: LICENSE
Requires-Dist: numpy>=1.19.0
Provides-Extra: dev
Requires-Dist: pytest>=6.0; extra == "dev"
Requires-Dist: pytest-cov>=2.0; extra == "dev"
Requires-Dist: black>=21.0; extra == "dev"
Requires-Dist: flake8>=3.8; extra == "dev"
Requires-Dist: jupyter>=1.0; extra == "dev"
Requires-Dist: matplotlib>=3.0; extra == "dev"
Requires-Dist: pandas>=1.0; extra == "dev"
Dynamic: author
Dynamic: author-email
Dynamic: classifier
Dynamic: description
Dynamic: description-content-type
Dynamic: home-page
Dynamic: keywords
Dynamic: license-file
Dynamic: project-url
Dynamic: provides-extra
Dynamic: requires-dist
Dynamic: requires-python
Dynamic: summary
